varwizard/__init__.py
varwizard/__main__.py
varwizard/cli.py
varwizard/config/__init__.py
varwizard/config/prefix_tuning.py
varwizard/data/__init__.py
varwizard/data/input_preparation.py
varwizard/generation/__init__.py
varwizard/generation/gen.py
varwizard/libs/tree-sitter/c.so
varwizard/libs/tree-sitter/c_sharp.so
varwizard/libs/tree-sitter/cpp.so
varwizard/libs/tree-sitter/go.so
varwizard/libs/tree-sitter/java.so
varwizard/libs/tree-sitter/javascript.so
varwizard/libs/tree-sitter/php.so
varwizard/libs/tree-sitter/python.so
varwizard/libs/tree-sitter/ruby.so
varwizard/libs/tree-sitter/rust.so
varwizard/models/__init__.py
varwizard/models/bloom.py
varwizard/models/codet5.py
varwizard/models/varwizard.py
varwizard/utils/__init__.py
varwizard/utils/obfuscation.py
varwizard-0.2.2.dist-info/METADATA
varwizard-0.2.2.dist-info/WHEEL
varwizard-0.2.2.dist-info/entry_points.txt
varwizard-0.2.2.dist-info/RECORD
