Metadata-Version: 2.1
Name: varwizard
Version: 0.2.2
Summary: An Automated Tool for Improving Code Quality Through Variable Name Refinement with Language Models
Home-page: https://github.com/FSoft-AI4Code/VarWizard
License: Apache-2.0
Keywords: variable renaming,language models,code quality
Author: FSoft-AI4Code
Author-email: support.aic@fpt.com
Requires-Python: >=3.7
Classifier: License :: OSI Approved :: Apache Software License
Classifier: Programming Language :: Python :: 3
Classifier: Programming Language :: Python :: 3.7
Classifier: Programming Language :: Python :: 3.8
Classifier: Programming Language :: Python :: 3.9
Classifier: Programming Language :: Python :: 3.10
Classifier: Programming Language :: Python :: 3.11
Requires-Dist: codetext
Requires-Dist: peft (==0.1.0)
Requires-Dist: torch (>=1.12.1)
Requires-Dist: transformers (>=4.28.0)
Requires-Dist: tree-sitter
Project-URL: Repository, https://github.com/FSoft-AI4Code/VarWizard
